.gitignore
mosaik_components/fmi/__init__.py
mosaik_components/fmi/mosaik_fmi.py
mosaik_components/fmi/parse_xml.py
mosaik_fmi-1.1.0.post0.dist-info/METADATA
mosaik_fmi-1.1.0.post0.dist-info/WHEEL
mosaik_fmi-1.1.0.post0.dist-info/licenses/AUTHORS.txt
mosaik_fmi-1.1.0.post0.dist-info/licenses/LICENSE
mosaik_fmi-1.1.0.post0.dist-info/RECORD
