Metadata-Version: 2.4
Name: mosaik-fmi
Version: 1.1.0.post0
Summary: An adapter for FMUs (ME or CS) in mosaik
Project-URL: Repository, https://gitlab.com/mosaik/components/mosaik-fmi
Project-URL: Documentation, https://gitlab.com/mosaik/components/mosaik-fmi
Project-URL: Discussions, https://github.com/orgs/OFFIS-mosaik/discussions
Author-email: Cornelius Steinbrink <mosaik@offis.de>
License-Expression: MIT
License-File: AUTHORS.txt
License-File: LICENSE
Classifier: Development Status :: 5 - Production/Stable
Classifier: Environment :: Console
Classifier: Intended Audience :: Science/Research
Classifier: License :: OSI Approved :: MIT License
Classifier: Natural Language :: English
Classifier: Operating System :: OS Independent
Classifier: Programming Language :: Python
Classifier: Programming Language :: Python :: 3
Classifier: Topic :: Scientific/Engineering
Classifier: Topic :: Software Development :: Libraries :: Python Modules
Requires-Python: >=3.9
Requires-Dist: fmipp>=2.0.0
Requires-Dist: mosaik-api-v3<4,>=3.0.4
